{
  "main": {
    "id": "60f3c90f9852323f",
    "type": "split",
    "children": [
      {
        "id": "a253f33f356912d2",
        "type": "tabs",
        "children": [
          {
            "id": "e2f35e0d4a3ab9b2",
            "type": "leaf",
            "state": {
              "type": "markdown",
              "state": {
                "file": "Game Design Doc.md",
                "mode": "source",
                "source": false
              },
              "icon": "lucide-file",
              "title": "Game Design Doc"
            }
          },
          {
            "id": "9d5e368bf825f8b1",
            "type": "leaf",
            "state": {
              "type": "markdown",
              "state": {
                "file": "Game Specs.md",
                "mode": "source",
                "source": false
              },
              "icon": "lucide-file",
              "title": "Game Specs"
            }
          },
          {
            "id": "8d4c836c4e935dc1",
            "type": "leaf",
            "state": {
              "type": "canvas",
              "state": {
                "file": "Production Methods.canvas",
                "viewState": {
                  "x": -375,
                  "y": -340,
                  "zoom": 0
                }
              },
              "icon": "lucide-layout-dashboard",
              "title": "Production Methods"
            }
          }
        ],
        "currentTab": 2
      }
    ],
    "direction": "vertical"
  },
  "left": {
    "id": "488d0ea4c64af9e7",
    "type": "split",
    "children": [
      {
        "id": "5d48373d6e093409",
        "type": "tabs",
        "children": [
          {
            "id": "af4baf14bd182838",
            "type": "leaf",
            "state": {
              "type": "file-explorer",
              "state": {
                "sortOrder": "alphabetical",
                "autoReveal": false
              },
              "icon": "lucide-folder-closed",
              "title": "Files"
            }
          },
          {
            "id": "709d9418135ae1a4",
            "type": "leaf",
            "state": {
              "type": "search",
              "state": {
                "query": "",
                "matchingCase": false,
                "explainSearch": false,
                "collapseAll": false,
                "extraContext": false,
                "sortOrder": "alphabetical"
              },
              "icon": "lucide-search",
              "title": "Search"
            }
          },
          {
            "id": "daee626e45bdd51f",
            "type": "leaf",
            "state": {
              "type": "bookmarks",
              "state": {},
              "icon": "lucide-bookmark",
              "title": "Bookmarks"
            }
          }
        ]
      }
    ],
    "direction": "horizontal",
    "width": 300
  },
  "right": {
    "id": "c1794e75600f5d8b",
    "type": "split",
    "children": [
      {
        "id": "ab40812b95cade92",
        "type": "tabs",
        "children": [
          {
            "id": "f1044b42f71788fe",
            "type": "leaf",
            "state": {
              "type": "backlink",
              "state": {
                "file": "Game Design Doc.md",
                "collapseAll": false,
                "extraContext": false,
                "sortOrder": "alphabetical",
                "showSearch": false,
                "searchQuery": "",
                "backlinkCollapsed": false,
                "unlinkedCollapsed": true
              },
              "icon": "links-coming-in",
              "title": "Backlinks for Game Design Doc"
            }
          },
          {
            "id": "2cb31d89e5ac6364",
            "type": "leaf",
            "state": {
              "type": "outgoing-link",
              "state": {
                "file": "Game Design Doc.md",
                "linksCollapsed": false,
                "unlinkedCollapsed": true
              },
              "icon": "links-going-out",
              "title": "Outgoing links from Game Design Doc"
            }
          },
          {
            "id": "679d8c5fd355d324",
            "type": "leaf",
            "state": {
              "type": "tag",
              "state": {
                "sortOrder": "frequency",
                "useHierarchy": true,
                "showSearch": false,
                "searchQuery": ""
              },
              "icon": "lucide-tags",
              "title": "Tags"
            }
          },
          {
            "id": "302bae1d581a8b31",
            "type": "leaf",
            "state": {
              "type": "all-properties",
              "state": {
                "sortOrder": "frequency",
                "showSearch": false,
                "searchQuery": ""
              },
              "icon": "lucide-archive",
              "title": "All properties"
            }
          },
          {
            "id": "7e5efce219183634",
            "type": "leaf",
            "state": {
              "type": "outline",
              "state": {
                "file": "Game Design Doc.md",
                "followCursor": false,
                "showSearch": false,
                "searchQuery": ""
              },
              "icon": "lucide-list",
              "title": "Outline of Game Design Doc"
            }
          }
        ]
      }
    ],
    "direction": "horizontal",
    "width": 300,
    "collapsed": true
  },
  "left-ribbon": {
    "hiddenItems": {
      "switcher:Open quick switcher": false,
      "graph:Open graph view": false,
      "canvas:Create new canvas": false,
      "daily-notes:Open today's daily note": false,
      "templates:Insert template": false,
      "command-palette:Open command palette": false,
      "bases:Create new base": false
    }
  },
  "active": "8d4c836c4e935dc1",
  "lastOpenFiles": [
    "Production.md",
    "Production Methods.canvas",
    "Game Specs.md",
    "Game Design Doc.md",
    "Population.md",
    "2026-06-28.md"
  ]
}